tonuino_cards_manager/__init__.py
tonuino_cards_manager/_card.py
tonuino_cards_manager/_clean.py
tonuino_cards_manager/_config.py
tonuino_cards_manager/_helpers.py
tonuino_cards_manager/_qrcode.py
tonuino_cards_manager/cover.py
tonuino_cards_manager/main.py
tonuino_cards_manager-0.3.0.dist-info/LICENSE
tonuino_cards_manager-0.3.0.dist-info/LICENSES/Apache-2.0.txt
tonuino_cards_manager-0.3.0.dist-info/LICENSES/CC0-1.0.txt
tonuino_cards_manager-0.3.0.dist-info/LICENSES/GPL-3.0-only.txt
tonuino_cards_manager-0.3.0.dist-info/METADATA
tonuino_cards_manager-0.3.0.dist-info/WHEEL
tonuino_cards_manager-0.3.0.dist-info/entry_points.txt
tonuino_cards_manager-0.3.0.dist-info/RECORD
