Metadata-Version: 2.3
Name: tonuino-cards-manager
Version: 0.3.0
Summary: Manage Tonuino RFID and SD cards by one configuration file. Easy, lightweight and feature-rich
License: GPL-3.0-only
Keywords: tonuino,management,automation
Author: Max Mehl
Author-email: mail@mehl.mx
Requires-Python: >=3.10,<4.0
Classifier: Development Status :: 5 - Production/Stable
Classifier: Environment :: Console
Classifier: Intended Audience :: End Users/Desktop
Classifier: License :: OSI Approved :: GNU General Public License v3 (GPLv3)
Classifier: Programming Language :: Python :: 3
Classifier: Programming Language :: Python :: 3.10
Classifier: Programming Language :: Python :: 3.11
Classifier: Programming Language :: Python :: 3.12
Classifier: Programming Language :: Python :: 3.13
Classifier: Topic :: Multimedia :: Sound/Audio
Classifier: Topic :: Utilities
Requires-Dist: mutagen (>=1.47.0,<2.0.0)
Requires-Dist: num2words (>=0.5.13,<0.6.0)
Requires-Dist: pyyaml (>=6.0.1,<7.0.0)
Requires-Dist: qrcode (>=8.1,<9.0)
Requires-Dist: wand (>=0.6.13,<0.7.0)
Project-URL: Repository, https://github.com/mxmehl/tonuino-cards-manager
